{
  "title": "Google Maps Data Extractor Input",
  "type": "object",
  "schemaVersion": 1,
  "properties": {
    "searchQuery": {
      "title": "Search Query",
      "type": "string",
      "description": "What to search for on Google Maps (e.g., 'restaurants', 'hotels', 'coffee shops')",
      "editor": "textfield",
      "example": "restaurants",
      "minLength": 1
    },
    "location": {
      "title": "Location",
      "type": "string",
      "description": "Where to search (e.g., 'Dubai', 'Kuwait City', 'Manama, Bahrain'). Leave empty to use Google's auto-detection.",
      "editor": "textfield",
      "example": "Dubai, UAE",
      "prefill": ""
    },
    "maxResults": {
      "title": "Maximum Results",
      "type": "integer",
      "description": "Maximum number of businesses to scrape. Set to 0 for unlimited. Default is 100.",
      "editor": "number",
      "minimum": 0,
      "default": 100,
      "unit": "businesses"
    },
    "scrapeDetails": {
      "title": "Scrape Business Details",
      "type": "boolean",
      "description": "Visit each business page to extract detailed information (address, phone, website, hours). This takes longer but provides complete data.",
      "editor": "checkbox",
      "default": false
    },
    "proxyConfiguration": {
      "title": "Proxy Configuration",
      "type": "object",
      "description": "Proxy settings for the scraper. Residential proxies are highly recommended for Google Maps to avoid blocking.",
      "editor": "proxy",
      "prefill": {
        "useApifyProxy": true,
        "apifyProxyGroups": ["RESIDENTIAL"]
      },
      "default": {
        "useApifyProxy": true,
        "apifyProxyGroups": ["RESIDENTIAL"]
      }
    },
    "minDelay": {
      "title": "Minimum Delay (seconds)",
      "type": "integer",
      "description": "Minimum delay between actions in seconds",
      "editor": "number",
      "minimum": 0,
      "maximum": 10,
      "default": 1,
      "unit": "seconds"
    },
    "maxDelay": {
      "title": "Maximum Delay (seconds)",
      "type": "integer",
      "description": "Maximum delay between actions in seconds",
      "editor": "number",
      "minimum": 1,
      "maximum": 20,
      "default": 3,
      "unit": "seconds"
    },
    "language": {
      "title": "Language",
      "type": "string",
      "description": "Language code for Google Maps results (e.g., 'en' for English, 'ar' for Arabic, 'fr' for French). Uses Google's hl parameter.",
      "editor": "textfield",
      "example": "en",
      "default": "en"
    },
    "debugScreenshots": {
      "title": "Debug Screenshots",
      "type": "boolean",
      "description": "Capture screenshots when errors occur for debugging purposes. Useful for troubleshooting but increases storage usage.",
      "editor": "checkbox",
      "default": false
    },
    "skipSponsored": {
      "sectionCaption": "Filtering Options",
      "title": "Skip Sponsored Listings",
      "type": "boolean",
      "description": "When enabled, skip all sponsored/ad listings and only return organic results.",
      "default": false
    },
    "skipWithWebsite": {
      "title": "Skip Listings With Website",
      "type": "boolean",
      "description": "When enabled, only return listings that do NOT have a website. Useful for finding businesses without web presence for lead generation.",
      "default": false
    },
    "skipWithPhone": {
      "title": "Skip Listings With Phone",
      "type": "boolean",
      "description": "When enabled, only return listings that do NOT have a phone number. Useful for finding businesses with incomplete contact info.",
      "default": false
    },
    "skipWithoutContact": {
      "title": "Skip Listings Without Contact Info",
      "type": "boolean",
      "description": "When enabled, skip listings that have neither a phone number nor email address. Only return listings with at least one contact method.",
      "default": false
    },
    "extractReviews": {
      "sectionCaption": "Review Extraction",
      "title": "Extract Reviews",
      "type": "boolean",
      "description": "When enabled, extract reviews for each business listing. This significantly increases scraping time as it requires visiting each business and loading all reviews.",
      "editor": "checkbox",
      "default": false
    },
    "maxReviews": {
      "title": "Maximum Reviews Per Business",
      "type": "integer",
      "description": "Maximum number of reviews to extract per business. Set to 0 or leave empty for unlimited (all reviews). Default is unlimited.",
      "editor": "number",
      "minimum": 0,
      "default": 0,
      "unit": "reviews"
    },
    "extractReviewShareLink": {
      "title": "Extract Review Share Links",
      "type": "boolean",
      "description": "When enabled, extract the shareable link for each review. This adds extra time as it requires clicking the share button for each review.",
      "editor": "checkbox",
      "default": false
    }
  },
  "required": ["searchQuery"]
}
